derivatecustomer.py
derivatecustomer-0.6.3.dist-info/LICENSE
derivatecustomer-0.6.3.dist-info/WHEEL
derivatecustomer-0.6.3.dist-info/METADATA
derivatecustomer-0.6.3.dist-info/RECORD
